{"name":"Gärri","aliases":["=-)",":-)","::--))",":)","............","Gärri","Just4Fun","Neocolor<3","TheNooby","UELI"],"steam64Id":76561198308879155,"accountId":348613427,"rankTier":52,"leaderBoardRank":null,"steamProfileUrl":"https://steamcommunity.com/profiles/76561198308879155/","steamAvatarUrl":"https://avatars.steamstatic.com/77ad4d858d567d7a97b9eb28f2efc3919df5c0d3.jpg","dotaBuffUrl":"https://www.dotabuff.com/players/348613427","openDotaUrl":"https://www.opendota.com/players/348613427","stratzUrl":"https://stratz.com/players/348613427","allTimeHeroes":[{"heroId":42,"heroName":"Wraith King","games":129,"wins":76,"laneRole":0,"lastPlayed":1773086181,"win_rate":58.91472868217055},{"heroId":6,"heroName":"Drow Ranger","games":86,"wins":47,"laneRole":0,"lastPlayed":1773260778,"win_rate":54.65116279069767},{"heroId":8,"heroName":"Juggernaut","games":81,"wins":40,"laneRole":0,"lastPlayed":1771768190,"win_rate":49.382716049382715},{"heroId":104,"heroName":"Legion Commander","games":62,"wins":36,"laneRole":0,"lastPlayed":1772831467,"win_rate":58.06451612903226},{"heroId":26,"heroName":"Lion","games":59,"wins":27,"laneRole":0,"lastPlayed":1772384736,"win_rate":45.76271186440678},{"heroId":102,"heroName":"Abaddon","games":46,"wins":22,"laneRole":0,"lastPlayed":1768058549,"win_rate":47.82608695652174},{"heroId":27,"heroName":"Shadow Shaman","games":37,"wins":20,"laneRole":0,"lastPlayed":1771439663,"win_rate":54.054054054054056},{"heroId":70,"heroName":"Ursa","games":37,"wins":20,"laneRole":0,"lastPlayed":1772881235,"win_rate":54.054054054054056},{"heroId":84,"heroName":"Ogre Magi","games":37,"wins":16,"laneRole":0,"lastPlayed":1772817832,"win_rate":43.24324324324324},{"heroId":12,"heroName":"Phantom Lancer","games":36,"wins":21,"laneRole":0,"lastPlayed":1773172225,"win_rate":58.333333333333336},{"heroId":75,"heroName":"Silencer","games":33,"wins":18,"laneRole":0,"lastPlayed":1765668224,"win_rate":54.54545454545454},{"heroId":85,"heroName":"Undying","games":29,"wins":17,"laneRole":0,"lastPlayed":1772390819,"win_rate":58.620689655172406},{"heroId":14,"heroName":"Pudge","games":27,"wins":12,"laneRole":0,"lastPlayed":1772834266,"win_rate":44.44444444444444},{"heroId":53,"heroName":"Nature's Prophet","games":23,"wins":9,"laneRole":0,"lastPlayed":1773095044,"win_rate":39.130434782608695},{"heroId":21,"heroName":"Windranger","games":20,"wins":6,"laneRole":0,"lastPlayed":1771775679,"win_rate":30.0},{"heroId":20,"heroName":"Vengeful Spirit","games":18,"wins":7,"laneRole":0,"lastPlayed":1771669548,"win_rate":38.88888888888889},{"heroId":22,"heroName":"Zeus","games":17,"wins":9,"laneRole":0,"lastPlayed":1772130293,"win_rate":52.94117647058824},{"heroId":30,"heroName":"Witch Doctor","games":17,"wins":7,"laneRole":0,"lastPlayed":1769708216,"win_rate":41.17647058823529},{"heroId":63,"heroName":"Weaver","games":17,"wins":7,"laneRole":0,"lastPlayed":1767733214,"win_rate":41.17647058823529},{"heroId":86,"heroName":"Rubick","games":16,"wins":9,"laneRole":0,"lastPlayed":1769900307,"win_rate":56.25},{"heroId":101,"heroName":"Skywrath Mage","games":16,"wins":10,"laneRole":0,"lastPlayed":1770324235,"win_rate":62.5},{"heroId":56,"heroName":"Clinkz","games":15,"wins":7,"laneRole":0,"lastPlayed":1772466570,"win_rate":46.666666666666664},{"heroId":45,"heroName":"Pugna","games":13,"wins":5,"laneRole":0,"lastPlayed":1762687716,"win_rate":38.46153846153847},{"heroId":64,"heroName":"Jakiro","games":13,"wins":5,"laneRole":0,"lastPlayed":1772822812,"win_rate":38.46153846153847},{"heroId":73,"heroName":"Alchemist","games":13,"wins":5,"laneRole":0,"lastPlayed":1767401068,"win_rate":38.46153846153847},{"heroId":2,"heroName":"Axe","games":10,"wins":0,"laneRole":0,"lastPlayed":1762893234,"win_rate":0.0},{"heroId":28,"heroName":"Slardar","games":9,"wins":4,"laneRole":0,"lastPlayed":1761413604,"win_rate":44.44444444444444},{"heroId":90,"heroName":"Keeper of the Light","games":7,"wins":2,"laneRole":0,"lastPlayed":1772394000,"win_rate":28.57142857142857},{"heroId":1,"heroName":"Anti-Mage","games":6,"wins":3,"laneRole":0,"lastPlayed":1772280089,"win_rate":50.0},{"heroId":137,"heroName":"Primal Beast","games":6,"wins":3,"laneRole":0,"lastPlayed":1771336877,"win_rate":50.0},{"heroId":23,"heroName":"Kunkka","games":5,"wins":3,"laneRole":0,"lastPlayed":1772838602,"win_rate":60.0},{"heroId":36,"heroName":"Necrophos","games":5,"wins":0,"laneRole":0,"lastPlayed":1765572396,"win_rate":0.0},{"heroId":96,"heroName":"Centaur Warrunner","games":5,"wins":3,"laneRole":0,"lastPlayed":1766948197,"win_rate":60.0},{"heroId":5,"heroName":"Crystal Maiden","games":4,"wins":2,"laneRole":0,"lastPlayed":1767465830,"win_rate":50.0},{"heroId":129,"heroName":"Mars","games":4,"wins":2,"laneRole":0,"lastPlayed":1767999513,"win_rate":50.0},{"heroId":19,"heroName":"Tiny","games":3,"wins":0,"laneRole":0,"lastPlayed":1772981376,"win_rate":0.0},{"heroId":43,"heroName":"Death Prophet","games":3,"wins":1,"laneRole":0,"lastPlayed":1760543053,"win_rate":33.33333333333333},{"heroId":46,"heroName":"Templar Assassin","games":3,"wins":1,"laneRole":0,"lastPlayed":1761431544,"win_rate":33.33333333333333},{"heroId":51,"heroName":"Clockwerk","games":3,"wins":1,"laneRole":0,"lastPlayed":1764501794,"win_rate":33.33333333333333},{"heroId":52,"heroName":"Leshrac","games":3,"wins":0,"laneRole":0,"lastPlayed":1769811407,"win_rate":0.0},{"heroId":29,"heroName":"Tidehunter","games":2,"wins":1,"laneRole":0,"lastPlayed":1766328688,"win_rate":50.0},{"heroId":32,"heroName":"Riki","games":2,"wins":1,"laneRole":0,"lastPlayed":1762643771,"win_rate":50.0},{"heroId":35,"heroName":"Sniper","games":2,"wins":0,"laneRole":0,"lastPlayed":1763820297,"win_rate":0.0},{"heroId":40,"heroName":"Venomancer","games":2,"wins":1,"laneRole":0,"lastPlayed":1772992746,"win_rate":50.0},{"heroId":50,"heroName":"Dazzle","games":2,"wins":1,"laneRole":0,"lastPlayed":1755929535,"win_rate":50.0},{"heroId":68,"heroName":"Ancient Apparition","games":2,"wins":0,"laneRole":0,"lastPlayed":1756315404,"win_rate":0.0},{"heroId":94,"heroName":"Medusa","games":2,"wins":1,"laneRole":0,"lastPlayed":1772189889,"win_rate":50.0},{"heroId":135,"heroName":"Dawnbreaker","games":2,"wins":2,"laneRole":0,"lastPlayed":1764436448,"win_rate":100.0},{"heroId":7,"heroName":"Earthshaker","games":1,"wins":0,"laneRole":0,"lastPlayed":1758987955,"win_rate":0.0},{"heroId":10,"heroName":"Morphling","games":1,"wins":0,"laneRole":0,"lastPlayed":1769623507,"win_rate":0.0},{"heroId":11,"heroName":"Shadow Fiend","games":1,"wins":0,"laneRole":0,"lastPlayed":1772134445,"win_rate":0.0},{"heroId":16,"heroName":"Sand King","games":1,"wins":0,"laneRole":0,"lastPlayed":1759666039,"win_rate":0.0},{"heroId":38,"heroName":"Beastmaster","games":1,"wins":1,"laneRole":0,"lastPlayed":1753803026,"win_rate":100.0},{"heroId":39,"heroName":"Queen of Pain","games":1,"wins":0,"laneRole":0,"lastPlayed":1755451833,"win_rate":0.0},{"heroId":47,"heroName":"Viper","games":1,"wins":0,"laneRole":0,"lastPlayed":1754074606,"win_rate":0.0},{"heroId":54,"heroName":"Lifestealer","games":1,"wins":1,"laneRole":0,"lastPlayed":1769022798,"win_rate":100.0},{"heroId":60,"heroName":"Night Stalker","games":1,"wins":0,"laneRole":0,"lastPlayed":1749418373,"win_rate":0.0},{"heroId":76,"heroName":"Outworld Destroyer","games":1,"wins":0,"laneRole":0,"lastPlayed":1754413502,"win_rate":0.0},{"heroId":105,"heroName":"Techies","games":1,"wins":0,"laneRole":0,"lastPlayed":1770237969,"win_rate":0.0},{"heroId":110,"heroName":"Phoenix","games":1,"wins":0,"laneRole":0,"lastPlayed":1767121496,"win_rate":0.0},{"heroId":123,"heroName":"Hoodwink","games":1,"wins":0,"laneRole":0,"lastPlayed":1772396984,"win_rate":0.0},{"heroId":136,"heroName":"Marci","games":1,"wins":0,"laneRole":0,"lastPlayed":1759574161,"win_rate":0.0}],"recentHeroes":[{"heroId":12,"heroName":"Phantom Lancer","games":15,"wins":11,"laneRole":0,"lastPlayed":1773172225,"win_rate":73.33333333333333},{"heroId":6,"heroName":"Drow Ranger","games":12,"wins":8,"laneRole":0,"lastPlayed":1773260778,"win_rate":66.66666666666666},{"heroId":42,"heroName":"Wraith King","games":12,"wins":7,"laneRole":0,"lastPlayed":1773086181,"win_rate":58.333333333333336},{"heroId":70,"heroName":"Ursa","games":11,"wins":5,"laneRole":0,"lastPlayed":1772881235,"win_rate":45.45454545454545},{"heroId":84,"heroName":"Ogre Magi","games":7,"wins":4,"laneRole":0,"lastPlayed":1772817832,"win_rate":57.14285714285714},{"heroId":8,"heroName":"Juggernaut","games":4,"wins":1,"laneRole":0,"lastPlayed":1771768190,"win_rate":25.0},{"heroId":26,"heroName":"Lion","games":4,"wins":1,"laneRole":0,"lastPlayed":1772384736,"win_rate":25.0},{"heroId":56,"heroName":"Clinkz","games":4,"wins":1,"laneRole":0,"lastPlayed":1772466570,"win_rate":25.0},{"heroId":1,"heroName":"Anti-Mage","games":3,"wins":1,"laneRole":0,"lastPlayed":1772280089,"win_rate":33.33333333333333},{"heroId":137,"heroName":"Primal Beast","games":3,"wins":2,"laneRole":0,"lastPlayed":1771336877,"win_rate":66.66666666666666},{"heroId":20,"heroName":"Vengeful Spirit","games":3,"wins":0,"laneRole":0,"lastPlayed":1771669548,"win_rate":0.0},{"heroId":22,"heroName":"Zeus","games":3,"wins":1,"laneRole":0,"lastPlayed":1772130293,"win_rate":33.33333333333333},{"heroId":53,"heroName":"Nature's Prophet","games":3,"wins":1,"laneRole":0,"lastPlayed":1773095044,"win_rate":33.33333333333333},{"heroId":19,"heroName":"Tiny","games":2,"wins":0,"laneRole":0,"lastPlayed":1772981376,"win_rate":0.0},{"heroId":23,"heroName":"Kunkka","games":2,"wins":1,"laneRole":0,"lastPlayed":1772838602,"win_rate":50.0},{"heroId":94,"heroName":"Medusa","games":2,"wins":1,"laneRole":0,"lastPlayed":1772189889,"win_rate":50.0},{"heroId":64,"heroName":"Jakiro","games":1,"wins":1,"laneRole":0,"lastPlayed":1772822812,"win_rate":100.0},{"heroId":11,"heroName":"Shadow Fiend","games":1,"wins":0,"laneRole":0,"lastPlayed":1772134445,"win_rate":0.0},{"heroId":14,"heroName":"Pudge","games":1,"wins":1,"laneRole":0,"lastPlayed":1772834266,"win_rate":100.0},{"heroId":85,"heroName":"Undying","games":1,"wins":1,"laneRole":0,"lastPlayed":1772390819,"win_rate":100.0},{"heroId":21,"heroName":"Windranger","games":1,"wins":0,"laneRole":0,"lastPlayed":1771775679,"win_rate":0.0},{"heroId":90,"heroName":"Keeper of the Light","games":1,"wins":0,"laneRole":0,"lastPlayed":1772394000,"win_rate":0.0},{"heroId":27,"heroName":"Shadow Shaman","games":1,"wins":0,"laneRole":0,"lastPlayed":1771439663,"win_rate":0.0},{"heroId":40,"heroName":"Venomancer","games":1,"wins":1,"laneRole":0,"lastPlayed":1772992746,"win_rate":100.0},{"heroId":104,"heroName":"Legion Commander","games":1,"wins":1,"laneRole":0,"lastPlayed":1772831467,"win_rate":100.0},{"heroId":123,"heroName":"Hoodwink","games":1,"wins":0,"laneRole":0,"lastPlayed":1772396984,"win_rate":0.0}],"competitiveHeroes":[{"heroId":27,"heroName":"Shadow Shaman","games":4,"wins":3,"laneRole":0,"lastPlayed":1764097418,"win_rate":75.0},{"heroId":26,"heroName":"Lion","games":3,"wins":2,"laneRole":0,"lastPlayed":1765738687,"win_rate":66.66666666666666},{"heroId":75,"heroName":"Silencer","games":2,"wins":1,"laneRole":0,"lastPlayed":1764617125,"win_rate":50.0},{"heroId":51,"heroName":"Clockwerk","games":2,"wins":0,"laneRole":0,"lastPlayed":1749423592,"win_rate":0.0},{"heroId":64,"heroName":"Jakiro","games":1,"wins":0,"laneRole":0,"lastPlayed":1765743718,"win_rate":0.0},{"heroId":96,"heroName":"Centaur Warrunner","games":1,"wins":1,"laneRole":0,"lastPlayed":1760985253,"win_rate":100.0},{"heroId":102,"heroName":"Abaddon","games":1,"wins":0,"laneRole":0,"lastPlayed":1763060859,"win_rate":0.0},{"heroId":42,"heroName":"Wraith King","games":1,"wins":0,"laneRole":0,"lastPlayed":1765307098,"win_rate":0.0},{"heroId":76,"heroName":"Outworld Destroyer","games":1,"wins":0,"laneRole":0,"lastPlayed":1754413502,"win_rate":0.0},{"heroId":14,"heroName":"Pudge","games":1,"wins":1,"laneRole":0,"lastPlayed":1762976722,"win_rate":100.0},{"heroId":20,"heroName":"Vengeful Spirit","games":1,"wins":0,"laneRole":0,"lastPlayed":1749376808,"win_rate":0.0},{"heroId":85,"heroName":"Undying","games":1,"wins":0,"laneRole":0,"lastPlayed":1754422282,"win_rate":0.0},{"heroId":60,"heroName":"Night Stalker","games":1,"wins":0,"laneRole":0,"lastPlayed":1749418373,"win_rate":0.0},{"heroId":30,"heroName":"Witch Doctor","games":1,"wins":1,"laneRole":0,"lastPlayed":1762972524,"win_rate":100.0},{"heroId":63,"heroName":"Weaver","games":1,"wins":1,"laneRole":0,"lastPlayed":1749387942,"win_rate":100.0}]}