{"id":"7c0ae6d26c0bee92d9150e3b5a0c4a6d1f1117f1a54763d18d505b02b3c98c8a","season":7,"league":8,"name":"Die Butterbande","rankTier":53,"miniProfileDTOS":[{"name":"MaJoR","aliases":[],"steam64Id":76561198035324102,"accountId":75058374,"rankTier":33,"leaderBoardRank":null,"steamProfileUrl":"https://steamcommunity.com/profiles/76561198035324102/","steamAvatarUrl":"https://avatars.steamstatic.com/f3d05db4d8557efbcdbfb337f4176abe9fcb5c1b.jpg","dotaBuffUrl":"https://www.dotabuff.com/players/75058374","openDotaUrl":"https://www.opendota.com/players/75058374","stratzUrl":"https://stratz.com/players/75058374","allTimeHeroes":[{"heroId":31,"heroName":"Lich","games":364,"wins":200,"laneRole":0,"lastPlayed":1772388875,"win_rate":54.94505494505495},{"heroId":26,"heroName":"Lion","games":283,"wins":149,"laneRole":0,"lastPlayed":1773261208,"win_rate":52.65017667844523},{"heroId":27,"heroName":"Shadow Shaman","games":272,"wins":147,"laneRole":0,"lastPlayed":1773002251,"win_rate":54.04411764705882},{"heroId":64,"heroName":"Jakiro","games":239,"wins":132,"laneRole":0,"lastPlayed":1772396679,"win_rate":55.23012552301255},{"heroId":37,"heroName":"Warlock","games":223,"wins":125,"laneRole":0,"lastPlayed":1770062007,"win_rate":56.05381165919282}],"mostRecentHeroes":[{"heroId":26,"heroName":"Lion","games":19,"wins":12,"laneRole":0,"lastPlayed":1773261208,"win_rate":63.1578947368421},{"heroId":27,"heroName":"Shadow Shaman","games":19,"wins":13,"laneRole":0,"lastPlayed":1773002251,"win_rate":68.42105263157895},{"heroId":64,"heroName":"Jakiro","games":12,"wins":6,"laneRole":0,"lastPlayed":1772396679,"win_rate":50.0},{"heroId":31,"heroName":"Lich","games":10,"wins":4,"laneRole":0,"lastPlayed":1772388875,"win_rate":40.0},{"heroId":112,"heroName":"Winter Wyvern","games":8,"wins":3,"laneRole":0,"lastPlayed":1772376525,"win_rate":37.5}],"competitiveHeroes":[{"heroId":27,"heroName":"Shadow Shaman","games":14,"wins":7,"laneRole":0,"lastPlayed":1768742808,"win_rate":50.0},{"heroId":26,"heroName":"Lion","games":10,"wins":5,"laneRole":0,"lastPlayed":1768748865,"win_rate":50.0},{"heroId":31,"heroName":"Lich","games":9,"wins":2,"laneRole":0,"lastPlayed":1761515284,"win_rate":22.22222222222222},{"heroId":64,"heroName":"Jakiro","games":5,"wins":3,"laneRole":0,"lastPlayed":1768656683,"win_rate":60.0},{"heroId":84,"heroName":"Ogre Magi","games":3,"wins":1,"laneRole":0,"lastPlayed":1732484424,"win_rate":33.33333333333333}]},{"name":"El Duderino","aliases":["El Duderino","El Duderino\uD83C\uDFAE\uD83D\uDC4C"],"steam64Id":76561197978688747,"accountId":18423019,"rankTier":51,"leaderBoardRank":null,"steamProfileUrl":"https://steamcommunity.com/id/Ph4t0n/","steamAvatarUrl":"https://avatars.steamstatic.com/621614c6ec4ecb93c36f2d1e655246db120efccb.jpg","dotaBuffUrl":"https://www.dotabuff.com/players/18423019","openDotaUrl":"https://www.opendota.com/players/18423019","stratzUrl":"https://stratz.com/players/18423019","allTimeHeroes":[{"heroId":30,"heroName":"Witch Doctor","games":321,"wins":192,"laneRole":0,"lastPlayed":1772921400,"win_rate":59.813084112149525},{"heroId":48,"heroName":"Luna","games":238,"wins":133,"laneRole":0,"lastPlayed":1773261208,"win_rate":55.88235294117647},{"heroId":14,"heroName":"Pudge","games":141,"wins":70,"laneRole":0,"lastPlayed":1765895101,"win_rate":49.645390070921984},{"heroId":25,"heroName":"Lina","games":139,"wins":68,"laneRole":0,"lastPlayed":1763409608,"win_rate":48.92086330935252},{"heroId":8,"heroName":"Juggernaut","games":134,"wins":62,"laneRole":0,"lastPlayed":1771709429,"win_rate":46.26865671641791}],"mostRecentHeroes":[{"heroId":36,"heroName":"Necrophos","games":14,"wins":7,"laneRole":0,"lastPlayed":1772919015,"win_rate":50.0},{"heroId":70,"heroName":"Ursa","games":9,"wins":5,"laneRole":0,"lastPlayed":1772829456,"win_rate":55.55555555555556},{"heroId":43,"heroName":"Death Prophet","games":9,"wins":5,"laneRole":0,"lastPlayed":1773258147,"win_rate":55.55555555555556},{"heroId":48,"heroName":"Luna","games":9,"wins":5,"laneRole":0,"lastPlayed":1773261208,"win_rate":55.55555555555556},{"heroId":30,"heroName":"Witch Doctor","games":7,"wins":4,"laneRole":0,"lastPlayed":1772921400,"win_rate":57.14285714285714}],"competitiveHeroes":[{"heroId":43,"heroName":"Death Prophet","games":11,"wins":7,"laneRole":0,"lastPlayed":1765728469,"win_rate":63.63636363636363},{"heroId":36,"heroName":"Necrophos","games":4,"wins":2,"laneRole":0,"lastPlayed":1765743577,"win_rate":50.0},{"heroId":30,"heroName":"Witch Doctor","games":4,"wins":2,"laneRole":0,"lastPlayed":1764529581,"win_rate":50.0},{"heroId":49,"heroName":"Dragon Knight","games":3,"wins":0,"laneRole":0,"lastPlayed":1765749114,"win_rate":0.0},{"heroId":31,"heroName":"Lich","games":3,"wins":1,"laneRole":0,"lastPlayed":1739823290,"win_rate":33.33333333333333}]},{"name":"manduca dota","aliases":["CONTRASTO","holi balboni","holi canoli","holy canoly","Kurt Bodowich angeschnallt","Kurt Bodowich est sur les nerves","Kurt Bodowich jetzt erst recht","Kurt Bodowich nimmt seinen Hut","manduca dota","Marco Giesel ist besiegbar"],"steam64Id":76561198131344517,"accountId":171078789,"rankTier":45,"leaderBoardRank":null,"steamProfileUrl":"https://steamcommunity.com/profiles/76561198131344517/","steamAvatarUrl":"https://avatars.steamstatic.com/a541a9f54c281bd40f8d81726a728b75b73f7df4.jpg","dotaBuffUrl":"https://www.dotabuff.com/players/171078789","openDotaUrl":"https://www.opendota.com/players/171078789","stratzUrl":"https://stratz.com/players/171078789","allTimeHeroes":[{"heroId":46,"heroName":"Templar Assassin","games":196,"wins":107,"laneRole":0,"lastPlayed":1773229248,"win_rate":54.59183673469388},{"heroId":42,"heroName":"Wraith King","games":155,"wins":92,"laneRole":0,"lastPlayed":1771787090,"win_rate":59.354838709677416},{"heroId":73,"heroName":"Alchemist","games":137,"wins":71,"laneRole":0,"lastPlayed":1744800620,"win_rate":51.82481751824818},{"heroId":53,"heroName":"Nature's Prophet","games":136,"wins":64,"laneRole":0,"lastPlayed":1770062531,"win_rate":47.05882352941176},{"heroId":94,"heroName":"Medusa","games":135,"wins":78,"laneRole":0,"lastPlayed":1772442308,"win_rate":57.77777777777777}],"mostRecentHeroes":[{"heroId":8,"heroName":"Juggernaut","games":36,"wins":17,"laneRole":0,"lastPlayed":1773222443,"win_rate":47.22222222222222},{"heroId":64,"heroName":"Jakiro","games":12,"wins":6,"laneRole":0,"lastPlayed":1773143004,"win_rate":50.0},{"heroId":46,"heroName":"Templar Assassin","games":10,"wins":6,"laneRole":0,"lastPlayed":1773229248,"win_rate":60.0},{"heroId":19,"heroName":"Tiny","games":9,"wins":4,"laneRole":0,"lastPlayed":1772619748,"win_rate":44.44444444444444},{"heroId":12,"heroName":"Phantom Lancer","games":6,"wins":2,"laneRole":0,"lastPlayed":1772815557,"win_rate":33.33333333333333}],"competitiveHeroes":[{"heroId":46,"heroName":"Templar Assassin","games":13,"wins":7,"laneRole":0,"lastPlayed":1768742808,"win_rate":53.84615384615385},{"heroId":94,"heroName":"Medusa","games":11,"wins":4,"laneRole":0,"lastPlayed":1768674730,"win_rate":36.36363636363637},{"heroId":54,"heroName":"Lifestealer","games":9,"wins":5,"laneRole":0,"lastPlayed":1768748865,"win_rate":55.55555555555556},{"heroId":42,"heroName":"Wraith King","games":5,"wins":2,"laneRole":0,"lastPlayed":1768668288,"win_rate":40.0},{"heroId":4,"heroName":"Bloodseeker","games":3,"wins":2,"laneRole":0,"lastPlayed":1768662799,"win_rate":66.66666666666666}]},{"name":"Turner","aliases":["Cobra McGavin","Ikaros","Is That Him?","Lee Richard der Miese Typ","Revy","Senjougahara","Turner","William Turner","Willow Taichou"],"steam64Id":76561198185174333,"accountId":224908605,"rankTier":61,"leaderBoardRank":null,"steamProfileUrl":"https://steamcommunity.com/id/turner1993/","steamAvatarUrl":"https://avatars.steamstatic.com/6d0897f4c7f144c96ed90e4f6f75400bdb81708b.jpg","dotaBuffUrl":"https://www.dotabuff.com/players/224908605","openDotaUrl":"https://www.opendota.com/players/224908605","stratzUrl":"https://stratz.com/players/224908605","allTimeHeroes":[{"heroId":104,"heroName":"Legion Commander","games":29,"wins":16,"laneRole":0,"lastPlayed":1772818547,"win_rate":55.172413793103445},{"heroId":2,"heroName":"Axe","games":21,"wins":14,"laneRole":0,"lastPlayed":1773258147,"win_rate":66.66666666666666},{"heroId":28,"heroName":"Slardar","games":21,"wins":14,"laneRole":0,"lastPlayed":1772820636,"win_rate":66.66666666666666},{"heroId":21,"heroName":"Windranger","games":14,"wins":6,"laneRole":0,"lastPlayed":1772386390,"win_rate":42.857142857142854},{"heroId":135,"heroName":"Dawnbreaker","games":14,"wins":12,"laneRole":0,"lastPlayed":1768742808,"win_rate":85.71428571428571}],"mostRecentHeroes":[{"heroId":104,"heroName":"Legion Commander","games":16,"wins":9,"laneRole":0,"lastPlayed":1772818547,"win_rate":56.25},{"heroId":155,"heroName":"Largo","games":11,"wins":7,"laneRole":0,"lastPlayed":1773261208,"win_rate":63.63636363636363},{"heroId":2,"heroName":"Axe","games":9,"wins":4,"laneRole":0,"lastPlayed":1773258147,"win_rate":44.44444444444444},{"heroId":28,"heroName":"Slardar","games":7,"wins":5,"laneRole":0,"lastPlayed":1772820636,"win_rate":71.42857142857143},{"heroId":21,"heroName":"Windranger","games":6,"wins":3,"laneRole":0,"lastPlayed":1772386390,"win_rate":50.0}],"competitiveHeroes":[{"heroId":28,"heroName":"Slardar","games":7,"wins":6,"laneRole":0,"lastPlayed":1768748865,"win_rate":85.71428571428571},{"heroId":2,"heroName":"Axe","games":4,"wins":4,"laneRole":0,"lastPlayed":1768737599,"win_rate":100.0},{"heroId":104,"heroName":"Legion Commander","games":4,"wins":2,"laneRole":0,"lastPlayed":1768674730,"win_rate":50.0},{"heroId":135,"heroName":"Dawnbreaker","games":3,"wins":2,"laneRole":0,"lastPlayed":1768742808,"win_rate":66.66666666666666},{"heroId":97,"heroName":"Magnus","games":2,"wins":1,"laneRole":0,"lastPlayed":1765743577,"win_rate":50.0}]},{"name":"Gucky","aliases":["Faptrap","Gruny","Guck$ter","Gucky","HACKER | Gucky","Less Gucky","Licence-Less Gucky","SEXY.-Less Gucky","российский жопа","Россия па́хнете"],"steam64Id":76561197997079911,"accountId":36814183,"rankTier":51,"leaderBoardRank":null,"steamProfileUrl":"https://steamcommunity.com/profiles/76561197997079911/","steamAvatarUrl":"https://avatars.steamstatic.com/360236e555049f204b12d3a8685a3b9b9764ebfe.jpg","dotaBuffUrl":"https://www.dotabuff.com/players/36814183","openDotaUrl":"https://www.opendota.com/players/36814183","stratzUrl":"https://stratz.com/players/36814183","allTimeHeroes":[{"heroId":86,"heroName":"Rubick","games":147,"wins":72,"laneRole":0,"lastPlayed":1772818547,"win_rate":48.97959183673469},{"heroId":21,"heroName":"Windranger","games":144,"wins":67,"laneRole":0,"lastPlayed":1764017130,"win_rate":46.52777777777778},{"heroId":30,"heroName":"Witch Doctor","games":114,"wins":60,"laneRole":0,"lastPlayed":1772655543,"win_rate":52.63157894736842},{"heroId":26,"heroName":"Lion","games":108,"wins":53,"laneRole":0,"lastPlayed":1770925069,"win_rate":49.074074074074076},{"heroId":31,"heroName":"Lich","games":104,"wins":56,"laneRole":0,"lastPlayed":1766318052,"win_rate":53.84615384615385}],"mostRecentHeroes":[{"heroId":86,"heroName":"Rubick","games":17,"wins":10,"laneRole":0,"lastPlayed":1772818547,"win_rate":58.82352941176471},{"heroId":123,"heroName":"Hoodwink","games":14,"wins":7,"laneRole":0,"lastPlayed":1772820636,"win_rate":50.0},{"heroId":26,"heroName":"Lion","games":7,"wins":4,"laneRole":0,"lastPlayed":1770925069,"win_rate":57.14285714285714},{"heroId":62,"heroName":"Bounty Hunter","games":6,"wins":3,"laneRole":0,"lastPlayed":1773258147,"win_rate":50.0},{"heroId":14,"heroName":"Pudge","games":5,"wins":3,"laneRole":0,"lastPlayed":1772135539,"win_rate":60.0}],"competitiveHeroes":[{"heroId":86,"heroName":"Rubick","games":7,"wins":5,"laneRole":0,"lastPlayed":1768742808,"win_rate":71.42857142857143},{"heroId":20,"heroName":"Vengeful Spirit","games":5,"wins":3,"laneRole":0,"lastPlayed":1768748865,"win_rate":60.0},{"heroId":31,"heroName":"Lich","games":4,"wins":3,"laneRole":0,"lastPlayed":1450814104,"win_rate":75.0},{"heroId":68,"heroName":"Ancient Apparition","games":3,"wins":3,"laneRole":0,"lastPlayed":1768737599,"win_rate":100.0},{"heroId":45,"heroName":"Pugna","games":2,"wins":1,"laneRole":0,"lastPlayed":1761508915,"win_rate":50.0}]},{"name":"Torben","aliases":[],"steam64Id":76561198031001301,"accountId":70735573,"rankTier":54,"leaderBoardRank":null,"steamProfileUrl":"https://steamcommunity.com/profiles/76561198031001301/","steamAvatarUrl":"https://avatars.steamstatic.com/2ad21217dc80fddb1f14c3fc33566ccbd2525560.jpg","dotaBuffUrl":"https://www.dotabuff.com/players/70735573","openDotaUrl":"https://www.opendota.com/players/70735573","stratzUrl":"https://stratz.com/players/70735573","allTimeHeroes":[{"heroId":74,"heroName":"Invoker","games":110,"wins":53,"laneRole":0,"lastPlayed":1759259811,"win_rate":48.18181818181818},{"heroId":25,"heroName":"Lina","games":80,"wins":38,"laneRole":0,"lastPlayed":1768674730,"win_rate":47.5},{"heroId":86,"heroName":"Rubick","games":71,"wins":24,"laneRole":0,"lastPlayed":1704488500,"win_rate":33.80281690140845},{"heroId":44,"heroName":"Phantom Assassin","games":68,"wins":42,"laneRole":0,"lastPlayed":1765912261,"win_rate":61.76470588235294},{"heroId":53,"heroName":"Nature's Prophet","games":68,"wins":39,"laneRole":0,"lastPlayed":1730838903,"win_rate":57.35294117647059}],"mostRecentHeroes":[{"heroId":21,"heroName":"Windranger","games":19,"wins":12,"laneRole":0,"lastPlayed":1773261208,"win_rate":63.1578947368421},{"heroId":25,"heroName":"Lina","games":7,"wins":3,"laneRole":0,"lastPlayed":1768674730,"win_rate":42.857142857142854},{"heroId":8,"heroName":"Juggernaut","games":6,"wins":4,"laneRole":0,"lastPlayed":1762203047,"win_rate":66.66666666666666},{"heroId":76,"heroName":"Outworld Destroyer","games":6,"wins":2,"laneRole":0,"lastPlayed":1768668288,"win_rate":33.33333333333333},{"heroId":36,"heroName":"Necrophos","games":6,"wins":3,"laneRole":0,"lastPlayed":1762974333,"win_rate":50.0}],"competitiveHeroes":[{"heroId":128,"heroName":"Snapfire","games":4,"wins":1,"laneRole":0,"lastPlayed":1741198036,"win_rate":25.0},{"heroId":74,"heroName":"Invoker","games":3,"wins":1,"laneRole":0,"lastPlayed":1743708106,"win_rate":33.33333333333333},{"heroId":123,"heroName":"Hoodwink","games":3,"wins":0,"laneRole":0,"lastPlayed":1741202517,"win_rate":0.0},{"heroId":35,"heroName":"Sniper","games":2,"wins":2,"laneRole":0,"lastPlayed":1763069534,"win_rate":100.0},{"heroId":119,"heroName":"Dark Willow","games":2,"wins":0,"laneRole":0,"lastPlayed":1743015755,"win_rate":0.0}]},{"name":"Lanfe4r#NoRagrets","aliases":["Lan4ear","Lanfe4r","Lanfe4r#NoMana","Lanfe4r#NoRagrets","MiriamelAnnai"],"steam64Id":76561198053893597,"accountId":93627869,"rankTier":45,"leaderBoardRank":null,"steamProfileUrl":"https://steamcommunity.com/profiles/76561198053893597/","steamAvatarUrl":"https://avatars.steamstatic.com/6bb794bc0d74936841fa74f2e20a0dcb11b15cd3.jpg","dotaBuffUrl":"https://www.dotabuff.com/players/93627869","openDotaUrl":"https://www.opendota.com/players/93627869","stratzUrl":"https://stratz.com/players/93627869","allTimeHeroes":[{"heroId":21,"heroName":"Windranger","games":402,"wins":198,"laneRole":0,"lastPlayed":1773175255,"win_rate":49.25373134328358},{"heroId":6,"heroName":"Drow Ranger","games":272,"wins":142,"laneRole":0,"lastPlayed":1772395413,"win_rate":52.20588235294118},{"heroId":94,"heroName":"Medusa","games":261,"wins":144,"laneRole":0,"lastPlayed":1768674886,"win_rate":55.172413793103445},{"heroId":56,"heroName":"Clinkz","games":235,"wins":131,"laneRole":0,"lastPlayed":1772985796,"win_rate":55.74468085106383},{"heroId":63,"heroName":"Weaver","games":231,"wins":105,"laneRole":0,"lastPlayed":1773003772,"win_rate":45.45454545454545}],"mostRecentHeroes":[{"heroId":56,"heroName":"Clinkz","games":10,"wins":8,"laneRole":0,"lastPlayed":1772985796,"win_rate":80.0},{"heroId":63,"heroName":"Weaver","games":9,"wins":6,"laneRole":0,"lastPlayed":1773003772,"win_rate":66.66666666666666},{"heroId":6,"heroName":"Drow Ranger","games":8,"wins":4,"laneRole":0,"lastPlayed":1772395413,"win_rate":50.0},{"heroId":70,"heroName":"Ursa","games":6,"wins":5,"laneRole":0,"lastPlayed":1773000497,"win_rate":83.33333333333334},{"heroId":21,"heroName":"Windranger","games":6,"wins":4,"laneRole":0,"lastPlayed":1773175255,"win_rate":66.66666666666666}],"competitiveHeroes":[{"heroId":6,"heroName":"Drow Ranger","games":10,"wins":3,"laneRole":0,"lastPlayed":1772395413,"win_rate":30.0},{"heroId":70,"heroName":"Ursa","games":7,"wins":5,"laneRole":0,"lastPlayed":1773000497,"win_rate":71.42857142857143},{"heroId":67,"heroName":"Spectre","games":5,"wins":3,"laneRole":0,"lastPlayed":1755112998,"win_rate":60.0},{"heroId":15,"heroName":"Razor","games":5,"wins":4,"laneRole":0,"lastPlayed":1768668288,"win_rate":80.0},{"heroId":94,"heroName":"Medusa","games":5,"wins":5,"laneRole":0,"lastPlayed":1768674886,"win_rate":100.0}]}]}