{"id":"c1a0377cee462c85930e2814c03948944a1d0295a1ebe22683ca651286f8e8b1","season":7,"league":8,"name":"Guardians of Groot","rankTier":62,"miniProfileDTOS":[{"name":"Rocket","aliases":["76561198070444042","I am going to TI 2025","I'll go to TI 2025","Rocket","Rocket (Pos 1) (LFT)","twitch.tv/rocket97"],"steam64Id":76561198070444042,"accountId":110178314,"rankTier":55,"leaderBoardRank":null,"steamProfileUrl":"https://steamcommunity.com/profiles/76561198070444042/","steamAvatarUrl":"https://avatars.steamstatic.com/c92fd06bdcf0d4557b1261ad665df77039075343.jpg","dotaBuffUrl":"https://www.dotabuff.com/players/110178314","openDotaUrl":"https://www.opendota.com/players/110178314","stratzUrl":"https://stratz.com/players/110178314","allTimeHeroes":[{"heroId":97,"heroName":"Magnus","games":376,"wins":179,"laneRole":0,"lastPlayed":1768668039,"win_rate":47.6063829787234},{"heroId":74,"heroName":"Invoker","games":362,"wins":175,"laneRole":0,"lastPlayed":1762718549,"win_rate":48.34254143646409},{"heroId":14,"heroName":"Pudge","games":353,"wins":205,"laneRole":0,"lastPlayed":1758387922,"win_rate":58.07365439093485},{"heroId":9,"heroName":"Mirana","games":237,"wins":143,"laneRole":0,"lastPlayed":1701485267,"win_rate":60.337552742616026},{"heroId":11,"heroName":"Shadow Fiend","games":209,"wins":107,"laneRole":0,"lastPlayed":1698499143,"win_rate":51.196172248803826}],"mostRecentHeroes":[{"heroId":53,"heroName":"Nature's Prophet","games":12,"wins":8,"laneRole":0,"lastPlayed":1767135142,"win_rate":66.66666666666666},{"heroId":97,"heroName":"Magnus","games":10,"wins":6,"laneRole":0,"lastPlayed":1768668039,"win_rate":60.0},{"heroId":70,"heroName":"Ursa","games":6,"wins":3,"laneRole":0,"lastPlayed":1768652039,"win_rate":50.0},{"heroId":7,"heroName":"Earthshaker","games":5,"wins":2,"laneRole":0,"lastPlayed":1766619151,"win_rate":40.0},{"heroId":54,"heroName":"Lifestealer","games":5,"wins":2,"laneRole":0,"lastPlayed":1768737599,"win_rate":40.0}],"competitiveHeroes":[{"heroId":54,"heroName":"Lifestealer","games":3,"wins":1,"laneRole":0,"lastPlayed":1768737599,"win_rate":33.33333333333333},{"heroId":97,"heroName":"Magnus","games":2,"wins":1,"laneRole":0,"lastPlayed":1768668039,"win_rate":50.0},{"heroId":70,"heroName":"Ursa","games":2,"wins":1,"laneRole":0,"lastPlayed":1768652039,"win_rate":50.0},{"heroId":8,"heroName":"Juggernaut","games":2,"wins":2,"laneRole":0,"lastPlayed":1768662664,"win_rate":100.0},{"heroId":74,"heroName":"Invoker","games":2,"wins":1,"laneRole":0,"lastPlayed":1762718549,"win_rate":50.0}]},{"name":"Sheepnade","aliases":["Chicknado","Chicknardo","Dubleboar","Dumbleboar","Dumbleboar aka Pigteor","No Doto Wood","Pigteor","Pointy Wood","Sheepnade","Sheepnale"],"steam64Id":76561198047445298,"accountId":87179570,"rankTier":63,"leaderBoardRank":null,"steamProfileUrl":"https://steamcommunity.com/profiles/76561198047445298/","steamAvatarUrl":"https://avatars.steamstatic.com/98120892ae754fc6c501d2dad7aa4e74efb9148b.jpg","dotaBuffUrl":"https://www.dotabuff.com/players/87179570","openDotaUrl":"https://www.opendota.com/players/87179570","stratzUrl":"https://stratz.com/players/87179570","allTimeHeroes":[{"heroId":76,"heroName":"Outworld Destroyer","games":8,"wins":2,"laneRole":0,"lastPlayed":1771160594,"win_rate":25.0},{"heroId":35,"heroName":"Sniper","games":6,"wins":5,"laneRole":0,"lastPlayed":1769892587,"win_rate":83.33333333333334},{"heroId":36,"heroName":"Necrophos","games":6,"wins":2,"laneRole":0,"lastPlayed":1769796788,"win_rate":33.33333333333333},{"heroId":86,"heroName":"Rubick","games":6,"wins":5,"laneRole":0,"lastPlayed":1769369959,"win_rate":83.33333333333334},{"heroId":7,"heroName":"Earthshaker","games":4,"wins":2,"laneRole":0,"lastPlayed":1770292815,"win_rate":50.0}],"mostRecentHeroes":[{"heroId":76,"heroName":"Outworld Destroyer","games":7,"wins":1,"laneRole":0,"lastPlayed":1771160594,"win_rate":14.285714285714285},{"heroId":36,"heroName":"Necrophos","games":6,"wins":2,"laneRole":0,"lastPlayed":1769796788,"win_rate":33.33333333333333},{"heroId":7,"heroName":"Earthshaker","games":4,"wins":2,"laneRole":0,"lastPlayed":1770292815,"win_rate":50.0},{"heroId":13,"heroName":"Puck","games":4,"wins":1,"laneRole":0,"lastPlayed":1769889892,"win_rate":25.0},{"heroId":35,"heroName":"Sniper","games":4,"wins":3,"laneRole":0,"lastPlayed":1769892587,"win_rate":75.0}],"competitiveHeroes":[{"heroId":86,"heroName":"Rubick","games":4,"wins":3,"laneRole":0,"lastPlayed":1768656850,"win_rate":75.0},{"heroId":35,"heroName":"Sniper","games":2,"wins":2,"laneRole":0,"lastPlayed":1762976722,"win_rate":100.0},{"heroId":7,"heroName":"Earthshaker","games":2,"wins":2,"laneRole":0,"lastPlayed":1762972524,"win_rate":100.0},{"heroId":112,"heroName":"Winter Wyvern","games":2,"wins":2,"laneRole":0,"lastPlayed":1741291631,"win_rate":100.0},{"heroId":57,"heroName":"Omniknight","games":2,"wins":1,"laneRole":0,"lastPlayed":1768667466,"win_rate":50.0}]},{"name":"bongomantiz","aliases":["BongoBoi","bongomantiz","censormantiz","Donald Trump","Eddie Smurphy","George Michael","negromantiz","pensibonsu","Skull-Bashar-al-Assad","Xavier Naidoo"],"steam64Id":76561197971589638,"accountId":11323910,"rankTier":45,"leaderBoardRank":null,"steamProfileUrl":"https://steamcommunity.com/profiles/76561197971589638/","steamAvatarUrl":"https://avatars.steamstatic.com/ab183c6d2ecc50a22eb68bfaec9cdaf8c1bbea41.jpg","dotaBuffUrl":"https://www.dotabuff.com/players/11323910","openDotaUrl":"https://www.opendota.com/players/11323910","stratzUrl":"https://stratz.com/players/11323910","allTimeHeroes":[{"heroId":21,"heroName":"Windranger","games":738,"wins":387,"laneRole":0,"lastPlayed":1771435378,"win_rate":52.4390243902439},{"heroId":36,"heroName":"Necrophos","games":572,"wins":323,"laneRole":0,"lastPlayed":1772045091,"win_rate":56.46853146853147},{"heroId":32,"heroName":"Riki","games":470,"wins":267,"laneRole":0,"lastPlayed":1769642772,"win_rate":56.80851063829787},{"heroId":5,"heroName":"Crystal Maiden","games":379,"wins":184,"laneRole":0,"lastPlayed":1771186738,"win_rate":48.54881266490765},{"heroId":4,"heroName":"Bloodseeker","games":333,"wins":185,"laneRole":0,"lastPlayed":1773259218,"win_rate":55.55555555555556}],"mostRecentHeroes":[{"heroId":126,"heroName":"Void Spirit","games":27,"wins":13,"laneRole":0,"lastPlayed":1772145809,"win_rate":48.148148148148145},{"heroId":36,"heroName":"Necrophos","games":9,"wins":5,"laneRole":0,"lastPlayed":1772045091,"win_rate":55.55555555555556},{"heroId":41,"heroName":"Faceless Void","games":6,"wins":2,"laneRole":0,"lastPlayed":1770328214,"win_rate":33.33333333333333},{"heroId":4,"heroName":"Bloodseeker","games":5,"wins":2,"laneRole":0,"lastPlayed":1773259218,"win_rate":40.0},{"heroId":31,"heroName":"Lich","games":5,"wins":4,"laneRole":0,"lastPlayed":1771002870,"win_rate":80.0}],"competitiveHeroes":[{"heroId":126,"heroName":"Void Spirit","games":3,"wins":1,"laneRole":0,"lastPlayed":1768737599,"win_rate":33.33333333333333},{"heroId":36,"heroName":"Necrophos","games":2,"wins":1,"laneRole":0,"lastPlayed":1768656683,"win_rate":50.0},{"heroId":32,"heroName":"Riki","games":1,"wins":0,"laneRole":0,"lastPlayed":1763316873,"win_rate":0.0},{"heroId":2,"heroName":"Axe","games":1,"wins":0,"laneRole":0,"lastPlayed":1761515284,"win_rate":0.0},{"heroId":4,"heroName":"Bloodseeker","games":1,"wins":1,"laneRole":0,"lastPlayed":1768668039,"win_rate":100.0}]},{"name":"Sainze","aliases":["CoD:Sainze","LudaHater","Nero<3","Ranger","Sainze","Sainze@DotaLan","Sainze | GER","ttv/Sainze","twitch.tv/Sainze","WendiLover"],"steam64Id":76561198006006250,"accountId":45740522,"rankTier":61,"leaderBoardRank":null,"steamProfileUrl":"https://steamcommunity.com/profiles/76561198006006250/","steamAvatarUrl":"https://avatars.steamstatic.com/a8b2802720b2a56eb76c98316b5a26c023b63f6b.jpg","dotaBuffUrl":"https://www.dotabuff.com/players/45740522","openDotaUrl":"https://www.opendota.com/players/45740522","stratzUrl":"https://stratz.com/players/45740522","allTimeHeroes":[{"heroId":6,"heroName":"Drow Ranger","games":373,"wins":209,"laneRole":0,"lastPlayed":1763847411,"win_rate":56.03217158176944},{"heroId":31,"heroName":"Lich","games":369,"wins":235,"laneRole":0,"lastPlayed":1772659979,"win_rate":63.68563685636857},{"heroId":104,"heroName":"Legion Commander","games":311,"wins":166,"laneRole":0,"lastPlayed":1772399964,"win_rate":53.37620578778135},{"heroId":63,"heroName":"Weaver","games":182,"wins":92,"laneRole":0,"lastPlayed":1766188921,"win_rate":50.54945054945055},{"heroId":121,"heroName":"Grimstroke","games":172,"wins":92,"laneRole":0,"lastPlayed":1771451461,"win_rate":53.48837209302325}],"mostRecentHeroes":[{"heroId":31,"heroName":"Lich","games":27,"wins":17,"laneRole":0,"lastPlayed":1772659979,"win_rate":62.96296296296296},{"heroId":26,"heroName":"Lion","games":9,"wins":4,"laneRole":0,"lastPlayed":1772574713,"win_rate":44.44444444444444},{"heroId":128,"heroName":"Snapfire","games":5,"wins":3,"laneRole":0,"lastPlayed":1772392104,"win_rate":60.0},{"heroId":30,"heroName":"Witch Doctor","games":5,"wins":3,"laneRole":0,"lastPlayed":1772318818,"win_rate":60.0},{"heroId":104,"heroName":"Legion Commander","games":5,"wins":3,"laneRole":0,"lastPlayed":1772399964,"win_rate":60.0}],"competitiveHeroes":[{"heroId":31,"heroName":"Lich","games":12,"wins":8,"laneRole":0,"lastPlayed":1764185125,"win_rate":66.66666666666666},{"heroId":27,"heroName":"Shadow Shaman","games":7,"wins":6,"laneRole":0,"lastPlayed":1763404923,"win_rate":85.71428571428571},{"heroId":26,"heroName":"Lion","games":4,"wins":2,"laneRole":0,"lastPlayed":1762895513,"win_rate":50.0},{"heroId":29,"heroName":"Tidehunter","games":3,"wins":2,"laneRole":0,"lastPlayed":1764182218,"win_rate":66.66666666666666},{"heroId":30,"heroName":"Witch Doctor","games":3,"wins":2,"laneRole":0,"lastPlayed":1762803379,"win_rate":66.66666666666666}]},{"name":"Jinzo","aliases":["Das MM hat immer Recht!","ich habe eine Axt","Jinzo","[NEC].Jinzo","Schlechter als karl geht eh nich","SheSaidSheWaslvl18","TVD Jinzo","TVD.Jinzo","WHY I HAVE TO PLAY THAT SHIT"],"steam64Id":76561198061071347,"accountId":100805619,"rankTier":24,"leaderBoardRank":null,"steamProfileUrl":"https://steamcommunity.com/profiles/76561198061071347/","steamAvatarUrl":"https://avatars.steamstatic.com/ede9c0fb818a03ae46b6f993ae1906f2cc174c57.jpg","dotaBuffUrl":"https://www.dotabuff.com/players/100805619","openDotaUrl":"https://www.opendota.com/players/100805619","stratzUrl":"https://stratz.com/players/100805619","allTimeHeroes":[{"heroId":97,"heroName":"Magnus","games":105,"wins":62,"laneRole":0,"lastPlayed":1769773872,"win_rate":59.04761904761905},{"heroId":86,"heroName":"Rubick","games":97,"wins":52,"laneRole":0,"lastPlayed":1744565966,"win_rate":53.608247422680414},{"heroId":45,"heroName":"Pugna","games":89,"wins":55,"laneRole":0,"lastPlayed":1768667466,"win_rate":61.79775280898876},{"heroId":79,"heroName":"Shadow Demon","games":78,"wins":44,"laneRole":0,"lastPlayed":1771435378,"win_rate":56.41025641025641},{"heroId":20,"heroName":"Vengeful Spirit","games":76,"wins":48,"laneRole":0,"lastPlayed":1766577422,"win_rate":63.1578947368421}],"mostRecentHeroes":[{"heroId":100,"heroName":"Tusk","games":22,"wins":8,"laneRole":0,"lastPlayed":1772572029,"win_rate":36.36363636363637},{"heroId":16,"heroName":"Sand King","games":16,"wins":8,"laneRole":0,"lastPlayed":1773083316,"win_rate":50.0},{"heroId":15,"heroName":"Razor","games":8,"wins":4,"laneRole":0,"lastPlayed":1772909685,"win_rate":50.0},{"heroId":19,"heroName":"Tiny","games":6,"wins":3,"laneRole":0,"lastPlayed":1772914925,"win_rate":50.0},{"heroId":90,"heroName":"Keeper of the Light","games":6,"wins":4,"laneRole":0,"lastPlayed":1772659979,"win_rate":66.66666666666666}],"competitiveHeroes":[{"heroId":45,"heroName":"Pugna","games":10,"wins":4,"laneRole":0,"lastPlayed":1768667466,"win_rate":40.0},{"heroId":79,"heroName":"Shadow Demon","games":9,"wins":4,"laneRole":0,"lastPlayed":1768651816,"win_rate":44.44444444444444},{"heroId":7,"heroName":"Earthshaker","games":4,"wins":2,"laneRole":0,"lastPlayed":1764102270,"win_rate":50.0},{"heroId":9,"heroName":"Mirana","games":3,"wins":3,"laneRole":0,"lastPlayed":1745437936,"win_rate":100.0},{"heroId":62,"heroName":"Bounty Hunter","games":3,"wins":0,"laneRole":0,"lastPlayed":1740078280,"win_rate":0.0}]},{"name":"Habuscho","aliases":[],"steam64Id":76561198147460121,"accountId":187194393,"rankTier":25,"leaderBoardRank":null,"steamProfileUrl":"https://steamcommunity.com/id/Habuscho/","steamAvatarUrl":"https://avatars.steamstatic.com/a549e4ba10b22b21fa6a7bed9ecfbaa8dc23f6d1.jpg","dotaBuffUrl":"https://www.dotabuff.com/players/187194393","openDotaUrl":"https://www.opendota.com/players/187194393","stratzUrl":"https://stratz.com/players/187194393","allTimeHeroes":[{"heroId":22,"heroName":"Zeus","games":292,"wins":150,"laneRole":0,"lastPlayed":1768337757,"win_rate":51.369863013698634},{"heroId":26,"heroName":"Lion","games":289,"wins":141,"laneRole":0,"lastPlayed":1773263244,"win_rate":48.78892733564014},{"heroId":47,"heroName":"Viper","games":276,"wins":139,"laneRole":0,"lastPlayed":1767646829,"win_rate":50.36231884057971},{"heroId":16,"heroName":"Sand King","games":192,"wins":108,"laneRole":0,"lastPlayed":1742750710,"win_rate":56.25},{"heroId":35,"heroName":"Sniper","games":186,"wins":86,"laneRole":0,"lastPlayed":1770578235,"win_rate":46.236559139784944}],"mostRecentHeroes":[{"heroId":75,"heroName":"Silencer","games":16,"wins":10,"laneRole":0,"lastPlayed":1772045091,"win_rate":62.5},{"heroId":26,"heroName":"Lion","games":12,"wins":5,"laneRole":0,"lastPlayed":1773263244,"win_rate":41.66666666666667},{"heroId":35,"heroName":"Sniper","games":10,"wins":6,"laneRole":0,"lastPlayed":1770578235,"win_rate":60.0},{"heroId":36,"heroName":"Necrophos","games":10,"wins":2,"laneRole":0,"lastPlayed":1769372609,"win_rate":20.0},{"heroId":64,"heroName":"Jakiro","games":9,"wins":6,"laneRole":0,"lastPlayed":1771435378,"win_rate":66.66666666666666}],"competitiveHeroes":[{"heroId":84,"heroName":"Ogre Magi","games":2,"wins":1,"laneRole":0,"lastPlayed":1768656683,"win_rate":50.0},{"heroId":101,"heroName":"Skywrath Mage","games":2,"wins":0,"laneRole":0,"lastPlayed":1764272250,"win_rate":0.0},{"heroId":26,"heroName":"Lion","games":2,"wins":0,"laneRole":0,"lastPlayed":1768652039,"win_rate":0.0},{"heroId":30,"heroName":"Witch Doctor","games":2,"wins":2,"laneRole":0,"lastPlayed":1768668039,"win_rate":100.0},{"heroId":64,"heroName":"Jakiro","games":1,"wins":1,"laneRole":0,"lastPlayed":1768662664,"win_rate":100.0}]},{"name":"rag3psych0","aliases":["a  litttle green groot","d0ntacre","DROW STRAT!!!!","Ein kleiner grüner Bam!","Ein kleiner grüner Baum!","ein kleiner grüner Groot","IAMGROOT #Baumi der Baum Baum","PornoPeter","rag3psych0","Smurfing like a pro"],"steam64Id":76561198159668753,"accountId":199403025,"rankTier":71,"leaderBoardRank":null,"steamProfileUrl":"https://steamcommunity.com/profiles/76561198159668753/","steamAvatarUrl":"https://avatars.steamstatic.com/c648a09d634e4f1a72d62831405abf571a22c3c2.jpg","dotaBuffUrl":"https://www.dotabuff.com/players/199403025","openDotaUrl":"https://www.opendota.com/players/199403025","stratzUrl":"https://stratz.com/players/199403025","allTimeHeroes":[{"heroId":8,"heroName":"Juggernaut","games":568,"wins":384,"laneRole":0,"lastPlayed":1762285611,"win_rate":67.6056338028169},{"heroId":70,"heroName":"Ursa","games":217,"wins":160,"laneRole":0,"lastPlayed":1761598058,"win_rate":73.73271889400922},{"heroId":48,"heroName":"Luna","games":163,"wins":111,"laneRole":0,"lastPlayed":1769976492,"win_rate":68.09815950920245},{"heroId":72,"heroName":"Gyrocopter","games":148,"wins":88,"laneRole":0,"lastPlayed":1749658565,"win_rate":59.45945945945946},{"heroId":1,"heroName":"Anti-Mage","games":132,"wins":87,"laneRole":0,"lastPlayed":1741903623,"win_rate":65.9090909090909}],"mostRecentHeroes":[{"heroId":72,"heroName":"Gyrocopter","games":21,"wins":14,"laneRole":0,"lastPlayed":1749658565,"win_rate":66.66666666666666},{"heroId":70,"heroName":"Ursa","games":14,"wins":11,"laneRole":0,"lastPlayed":1761598058,"win_rate":78.57142857142857},{"heroId":8,"heroName":"Juggernaut","games":10,"wins":4,"laneRole":0,"lastPlayed":1762285611,"win_rate":40.0},{"heroId":42,"heroName":"Wraith King","games":7,"wins":7,"laneRole":0,"lastPlayed":1744813470,"win_rate":100.0},{"heroId":94,"heroName":"Medusa","games":5,"wins":5,"laneRole":0,"lastPlayed":1762291210,"win_rate":100.0}],"competitiveHeroes":[{"heroId":70,"heroName":"Ursa","games":16,"wins":14,"laneRole":0,"lastPlayed":1746879045,"win_rate":87.5},{"heroId":72,"heroName":"Gyrocopter","games":13,"wins":9,"laneRole":0,"lastPlayed":1743361922,"win_rate":69.23076923076923},{"heroId":8,"heroName":"Juggernaut","games":12,"wins":8,"laneRole":0,"lastPlayed":1760727417,"win_rate":66.66666666666666},{"heroId":89,"heroName":"Naga Siren","games":8,"wins":5,"laneRole":0,"lastPlayed":1742411445,"win_rate":62.5},{"heroId":54,"heroName":"Lifestealer","games":6,"wins":4,"laneRole":0,"lastPlayed":1746882366,"win_rate":66.66666666666666}]}]}